edupfr/__init__.py
edupfr/_m3_imports.py
edupfr/snils_by_data/__init__.py
edupfr/snils_by_data/actions.py
edupfr/snils_by_data/helpers.py
edupfr/snils_by_data/settings.py
edupfr/snils_by_data/snils-request-button.js
edupfr/snils_by_data/ui.py
edupfr-0.3.0.dist-info/METADATA
edupfr-0.3.0.dist-info/WHEEL
edupfr-0.3.0.dist-info/dependency_links.txt
edupfr-0.3.0.dist-info/top_level.txt
edupfr-0.3.0.dist-info/RECORD
