Metadata-Version: 2.1
Name: edupfr
Version: 0.3.0
Summary: Клиенты для веб-сервисов Пенсионного фонда РФ
Home-page: https://stash.bars-open.ru/projects/EDUBASE/repos/edupfr
Author: BARS Group
Author-email: bars@bars-open.ru
License: MIT
